{"data":{"allContentfulBlog":{"edges":[{"node":{"title":"The best interiors of fashion houses","createdAt":"May 23rd, 2019","slug":"best-interiors","thumbnail":{"file":{"url":"//images.ctfassets.net/gwdbp229r860/5gq9tXa2JW2tefoZTXPsx4/414f978b7b1dc77a27623753a1724200/slice2.png"}}}},{"node":{"title":"7 Main rules before starting a design","createdAt":"May 23rd, 2019","slug":"7-rules","thumbnail":{"file":{"url":"//images.ctfassets.net/gwdbp229r860/5gq9tXa2JW2tefoZTXPsx4/414f978b7b1dc77a27623753a1724200/slice2.png"}}}},{"node":{"title":"The German Institute of Architecture has developed a new construction technology","createdAt":"May 23rd, 2019","slug":"german-technology","thumbnail":{"file":{"url":"//images.ctfassets.net/gwdbp229r860/5gq9tXa2JW2tefoZTXPsx4/414f978b7b1dc77a27623753a1724200/slice2.png"}}}},{"node":{"title":"The German Institute of Architecture has developed a new construction technology","createdAt":"May 23rd, 2019","slug":"german-architecture","thumbnail":{"file":{"url":"//images.ctfassets.net/gwdbp229r860/5gq9tXa2JW2tefoZTXPsx4/414f978b7b1dc77a27623753a1724200/slice2.png"}}}},{"node":{"title":"7 Main rules before starting a design","createdAt":"May 23rd, 2019","slug":"starting-design","thumbnail":{"file":{"url":"//images.ctfassets.net/gwdbp229r860/5gq9tXa2JW2tefoZTXPsx4/414f978b7b1dc77a27623753a1724200/slice2.png"}}}},{"node":{"title":"The best interiors of fashion houses","createdAt":"May 23rd, 2019","slug":"interiors","thumbnail":{"file":{"url":"//images.ctfassets.net/gwdbp229r860/5gq9tXa2JW2tefoZTXPsx4/414f978b7b1dc77a27623753a1724200/slice2.png"}}}}]}}}